FastHMM/__init__.py
FastHMM/hmm.py
FastHMM/non_rec_viterbi.py
FastHMM-0.1.2.dist-info/LICENSE.txt
FastHMM-0.1.2.dist-info/METADATA
FastHMM-0.1.2.dist-info/WHEEL
FastHMM-0.1.2.dist-info/top_level.txt
FastHMM-0.1.2.dist-info/RECORD
