Metadata-Version: 2.1
Name: FastHMM
Version: 0.1.2
Summary: A python package for HMM model with fast train and decoding implementation
Home-page: https://github.com/312shan/FastHMM
Author: Yunshan Chen
Author-email: chenyunshan312@163.com
License: UNKNOWN
Keywords: hmm viterbi
Platform: UNKNOWN
Classifier: Programming Language :: Python :: 3
Classifier: License :: OSI Approved :: MIT License
Classifier: Operating System :: OS Independent
Requires-Python: >=3.5
Requires-Dist: pathlib ; python_version < "3.4"
Requires-Dist: typing ; python_version < "3.5"
